README.md
setup.cfg
setup.py
bcinfo/__init__.py
bcinfo/search.py
bcinfo/test.py
bcinfo.egg-info/PKG-INFO
bcinfo.egg-info/SOURCES.txt
bcinfo.egg-info/dependency_links.txt
bcinfo.egg-info/entry_points.txt
bcinfo.egg-info/requires.txt
bcinfo.egg-info/top_level.txt