Metadata-Version: 2.1
Name: bcinfo
Version: 0.0.3
Summary: A python project for accummulation of my works before.
Home-page: https://github.com/hsiaoyi0504/bcinfo
Author: Yi Hsiao
Author-email: hsiaoyi0504@gmail.com
License: UNKNOWN
Project-URL: Source, https://github.com/hsiaoyi0504/bcinfo/
Project-URL: Bug Reports, https://github.com/hsiaoyi0504/bcinfo/issues
Keywords: bioinformatics cheminformatics
Platform: UNKNOWN
Classifier: Development Status :: 3 - Alpha
Classifier: Intended Audience :: Developers
Classifier: Topic :: Software Development :: Build Tools
Classifier: License :: OSI Approved :: MIT License
Classifier: Programming Language :: Python :: 2
Classifier: Programming Language :: Python :: 2.7
Classifier: Programming Language :: Python :: 3
Classifier: Programming Language :: Python :: 3.4
Classifier: Programming Language :: Python :: 3.5
Classifier: Programming Language :: Python :: 3.6
Provides-Extra: test
Provides-Extra: dev
